pyezoo/__init__.py
pyezoo/connections.py
pyezoo/cursors.py
pyezoo/error.py
pyezoo/ezoo_log.py
pyezoo/times.py
pyezoo/config/__init__.py
pyezoo/config/config.py
pyezoo/constants/ER.py
pyezoo/constants/FIELD_TYPE.py
pyezoo/constants/__init__.py
pyezoo/gen/__init__.py
pyezoo/gen/ezooapi_algorithm/__init__.py
pyezoo/gen/ezooapi_algorithm/constants.py
pyezoo/gen/ezooapi_algorithm/ezooapi_algorithm.py
pyezoo/gen/ezooapi_algorithm/ttypes.py
pyezoo/gen/ezooapi_auth/__init__.py
pyezoo/gen/ezooapi_auth/constants.py
pyezoo/gen/ezooapi_auth/ezooapi_auth.py
pyezoo/gen/ezooapi_auth/ttypes.py
pyezoo/gen/ezooapi_base/__init__.py
pyezoo/gen/ezooapi_base/constants.py
pyezoo/gen/ezooapi_base/ezooapi_base.py
pyezoo/gen/ezooapi_base/ttypes.py
pyezoo/gen/ezooapi_client/__init__.py
pyezoo/gen/ezooapi_client/constants.py
pyezoo/gen/ezooapi_client/ezooapi_client.py
pyezoo/gen/ezooapi_client/ttypes.py
pyezoo/gen/ezooapi_data/__init__.py
pyezoo/gen/ezooapi_data/constants.py
pyezoo/gen/ezooapi_data/ezooapi_data.py
pyezoo/gen/ezooapi_data/ttypes.py
pyezoo/gen/ezoocommon/__init__.py
pyezoo/gen/ezoocommon/constants.py
pyezoo/gen/ezoocommon/ttypes.py
pyezoo/gen/ezootypes/__init__.py
pyezoo/gen/ezootypes/constants.py
pyezoo/gen/ezootypes/ttypes.py
pyezoo/loadbalance/__init__.py
pyezoo/loadbalance/strategy.py
pyezoo/pool/__init__.py
pyezoo/pool/driver.py
pyezoo/pool/ezooapi.py
pyezoo/pool/ezoodb_client.py
pyezoo/pool/pooled_db.py
pyezoo/pool/pooled_distribute.py
pyezoo/pool/steady_db.py
pyezoo/utils/__init__.py
pyezoo/utils/codec_util.py
pyezoo-2.0.1.dist-info/METADATA
pyezoo-2.0.1.dist-info/WHEEL
pyezoo-2.0.1.dist-info/top_level.txt
pyezoo-2.0.1.dist-info/RECORD
