Metadata-Version: 2.1
Name: pyezoo
Version: 2.0.1
Summary: python3 sdk for ezoodb.
Home-page: https://www.ezoodb.com
Author: eZoo
Author-email: ezoo@ezoodb.com
Project-URL: Documentation, https://www.ezoodb.com/ezoo-doc?u=/doc/3.eZoo%25E6%258A%2580%25E6%259C%25AF%25E6%2589%258B%25E5%2586%258C/5.eZoo-API/
Requires: thrift
Requires-Python: >=3.7
Requires-Dist: thrift
